pyiter/__init__.py
pyiter/combination.py
pyiter/concat.py
pyiter/dedup.py
pyiter/distinct.py
pyiter/drop.py
pyiter/drop_while.py
pyiter/error.py
pyiter/filtering.py
pyiter/flattening.py
pyiter/grouping.py
pyiter/intersection.py
pyiter/list_like.py
pyiter/mapping.py
pyiter/merging.py
pyiter/merging_with_next.py
pyiter/parallel_mapping.py
pyiter/sequence.py
pyiter/shuffling.py
pyiter/take.py
pyiter/take_while.py
pyiter/transform.py
pyiter/type_guard.py
pyiter/windowed.py
pyiter-0.13.9.dist-info/licenses/LICENSE-APACHE
pyiter-0.13.9.dist-info/licenses/LICENSE-MIT
pyiter-stubs/__init__.pyi
pyiter-stubs/combination.pyi
pyiter-stubs/concat.pyi
pyiter-stubs/dedup.pyi
pyiter-stubs/distinct.pyi
pyiter-stubs/drop.pyi
pyiter-stubs/drop_while.pyi
pyiter-stubs/error.pyi
pyiter-stubs/filtering.pyi
pyiter-stubs/flattening.pyi
pyiter-stubs/grouping.pyi
pyiter-stubs/intersection.pyi
pyiter-stubs/list_like.pyi
pyiter-stubs/mapping.pyi
pyiter-stubs/merging.pyi
pyiter-stubs/merging_with_next.pyi
pyiter-stubs/parallel_mapping.pyi
pyiter-stubs/sequence.pyi
pyiter-stubs/shuffling.pyi
pyiter-stubs/take.pyi
pyiter-stubs/take_while.pyi
pyiter-stubs/transform.pyi
pyiter-stubs/type_guard.pyi
pyiter-stubs/windowed.pyi
pyiter-0.13.9.dist-info/METADATA
pyiter-0.13.9.dist-info/WHEEL
pyiter-0.13.9.dist-info/top_level.txt
pyiter-0.13.9.dist-info/RECORD
