Metadata-Version: 2.4
Name: pyiter
Version: 0.13.9
Summary: PyIter is a Python package for iterative operations inspired by the Kotlin、CSharp(linq)、TypeSrcipt and Rust. Enables strong typing and type inference for iterative operations.
Author-email: YISH <mokeyish@hotmail.com>
Requires-Python: >=3.10
License-File: LICENSE-APACHE
License-File: LICENSE-MIT
Requires-Dist: typing-extensions>=4.14.0
Dynamic: license-file
